Workbook

Sheet Master_Sheet
A1: Year | B1: Revenue | C1: Operating Profit | D1: Net Profit | E1: Total Assets | F1: Total Liabilities | G1: Equity
A2: 2019 | B2: 146463 | C2: 39506 | D2: 31472 | E2: 113901 | F2: 113901 | G2: =375+'[1]Balance Sheet'!$E$5 -> 89446
A3: 2020 | B3: 156949 | C3: 42109 | D3: 32340 | E3: 120127 | F3: 120127 | G3: ='[1]Balance Sheet'!$F$5+375 -> 84126
A4: 2021 | B4: 164177 | C4: 46546 | D4: 32430 | E4: 129992 | F4: 129992 | G4: =370+'[1]Balance Sheet'!$G$5 -> 86433
A5: 2022 | B5: 191754 | C5: 53057 | D5: 38327 | E5: 140924 | F5: 140924 | G5: ='[1]Balance Sheet'!$H$5+366 -> 89139
A6: 2023 | B6: 225458 | C6: 59259 | D6: 42147 | E6: 142859 | F6: 142859 | G6: ='[1]Balance Sheet'!$I$5+366 -> 90424
A7: 2024 | B7: 240893 | C7: 64296 | D7: 45908 | E7: 145472 | F7: 145472 | G7: =+'[1]Balance Sheet'!$J$5+362 -> 90489
A8: 2025 | B8: 255324 | C8: 67407 | D8: 48553 | E8: 158649 | F8: 158649 | G8: ='[1]Balance Sheet'!$K$5+362 -> 94756

Sheet financial_analysis
A1: ROE | B1: ROA | C1: Operating Margin | D1: Net Profit Margin | E1: Revenue Growth %
A2: =Master_Sheet!D2/Master_Sheet!G2 -> 0.35185475 | B2: =Master_Sheet!D2/Master_Sheet!E2 -> 0.27631013 | C2: =Master_Sheet!C2/Master_Sheet!B2 -> 0.26973365 | D2: =Master_Sheet!D2/Master_Sheet!B2 -> 0.21488021 | E2: =(Master_Sheet!B2-123104)/123104 -> 0.18975013
A3: =Master_Sheet!D3/Master_Sheet!G3 -> 0.38442336 | B3: =Master_Sheet!D3/Master_Sheet!E3 -> 0.26921508 | C3: =Master_Sheet!C3/Master_Sheet!B3 -> 0.26829734 | D3: =Master_Sheet!D3/Master_Sheet!B3 -> 0.2060542 | E3: =(Master_Sheet!B3-123104)/123104 -> 0.27493014
A4: =Master_Sheet!D4/Master_Sheet!G4 -> 0.37520392 | B4: =Master_Sheet!D4/Master_Sheet!E4 -> 0.24947689 | C4: =Master_Sheet!C4/Master_Sheet!B4 -> 0.28351109 | D4: =Master_Sheet!D4/Master_Sheet!B4 -> 0.19753071 | E4: =(Master_Sheet!B4-123104)/123104 -> 0.33364472
A5: =Master_Sheet!D5/Master_Sheet!G5 -> 0.42996892 | B5: =Master_Sheet!D5/Master_Sheet!E5 -> 0.27196929 | C5: =Master_Sheet!C5/Master_Sheet!B5 -> 0.27669305 | D5: =Master_Sheet!D5/Master_Sheet!B5 -> 0.19987588 | E5: =(Master_Sheet!B5-123104)/123104 -> 0.55765857
A6: =Master_Sheet!D6/Master_Sheet!G6 -> 0.46610413 | B6: =Master_Sheet!D6/Master_Sheet!E6 -> 0.29502516 | C6: =Master_Sheet!C6/Master_Sheet!B6 -> 0.26283831 | D6: =Master_Sheet!D6/Master_Sheet!B6 -> 0.18693947 | E6: =(Master_Sheet!B6-123104)/123104 -> 0.83144333
A7: =Master_Sheet!D7/Master_Sheet!G7 -> 0.50733238 | B7: =Master_Sheet!D7/Master_Sheet!E7 -> 0.31557963 | C7: =Master_Sheet!C7/Master_Sheet!B7 -> 0.26690688 | D7: =Master_Sheet!D7/Master_Sheet!B7 -> 0.19057424 | E7: =(Master_Sheet!B7-123104)/123104 -> 0.95682512
A8: =Master_Sheet!D8/Master_Sheet!G8 -> 0.51240027 | B8: =Master_Sheet!D8/Master_Sheet!E8 -> 0.30604038 | C8: =Master_Sheet!C8/Master_Sheet!B8 -> 0.26400573 | D8: =Master_Sheet!D8/Master_Sheet!B8 -> 0.1901623 | E8: =(Master_Sheet!B8-123104)/123104 -> 1.0740512
